README.txt
setup.py
mymat/__init__.py
mymat/denoise.py
mymat/linalg.py
mymat/matdemo.py
mymat/matshow.py
mymat/mymat.py
mymat/test_mat.py
mymat.egg-info/PKG-INFO
mymat.egg-info/SOURCES.txt
mymat.egg-info/dependency_links.txt
mymat.egg-info/top_level.txt
mymat.egg-info/zip-safe