Metadata-Version: 1.1
Name: mymat
Version: 1.1.0
Summary: Subclass of numpy.matrix behaving as matrices in matlab.
Home-page: https://git.oschina.net/williamzjc/mymat
Author: William Song
Author-email: songcwzjut@163.com
License: MIT
Keywords: numpy matrix matlab
Platform: UNKNOWN
Classifier: License :: Public Domain
Classifier: Programming Language :: Python
Classifier: Programming Language :: Python :: 3.4
Classifier: Intended Audience :: Science/Research
Classifier: Operating System :: OS Independent
Classifier: Topic :: Scientific/Engineering :: Mathematics
Classifier: Natural Language :: English
